<?xml version="1.0" encoding="UTF-8" standalone="yes"?><Family_Data><Family_Member memberName="ram"><age>22</age><disease>1</disease><disease_symp>1,2</disease_symp><dob>20-10-1995</dob><gender>1</gender><relation>self</relation><sr_no>1</sr_no></Family_Member><survey hofName="ram" rashanId="3425325545345"><asha_member>Item 3</asha_member><bhamasha>wetwere</bhamasha><district>Ajmer</district><f_members>1</f_members><food_plan>false</food_plan><form_num>485697548</form_num><health_centre>Item 4</health_centre><health_insurance>1236548956325648765</health_insurance><mobile>7856945689</mobile><phc>Badakhera</phc><status>true</status><village>Aakhri--(Srinagar)</village></survey></Family_Data>